zero_one_detector/zero_one_detector.v
module zero_one_detector(
    input  clk,
    input rst,
    input A,
    output reg Y
    );
parameter S0 = 2'b00;
parameter S1 = 2'b01;
parameter S2 = 2'b10;
reg [1:0] curr_state;
reg [1:0] nxt_state;

always@(posedge clk)
    begin
    if(rst)
        begin
        curr_state <= S0;
        Y = 0;
        end
    else
        curr_state <= nxt_state;
    end
always@(*)
    begin
    case(curr_state)
        S0:
            if(A == 1'b1)
                begin
                nxt_state <= S0;
                end
            else
                begin
                nxt_state <= S1;
                end
        S1:
            if(A == 1'b1)
                begin
                nxt_state <= S2;
                end
            else
                begin
                nxt_state <= S1;
                end
        S2:
            if(A == 1'b1)
                begin
                nxt_state <= S0;
                end
            else
                begin
                nxt_state <= S1;
                end
        default: nxt_state <= S0;
    endcase
    end
always@(posedge clk)
    begin
        if(nxt_state == S2)
            Y = 1'b1;
        else
            Y = 1'b0;

    end
endmodule

zero_one_detector/zero_one_detector_tb.v
module seq_tb;
    reg A;
    reg clk;
    reg rst;
    wire Y;

    zero_one_detector uut(
        .A(A),
        .clk(clk),
        .rst(rst),
        .Y(Y)
        );

    initial begin
        $dumpfile("zero_one_detector.vcd");
        $dumpvars(0,seq_tb);
        rst = 1;
        #50
        rst = 0;

        #50

        clk = 0;
        A = 0;

        #50

        clk = 1;

        #50

        clk = 0;

        #50

        clk = 1;

        #20

        A = 1;

        #30

        clk = 0;

        #50

        clk = 1;

        #10

        A = 0;

        #40

        clk = 0;

        #50

        clk = 1;

        #50

        clk = 0;

        #10

        A = 1;

        #40

        clk = 1;

        #50

        clk = 0;

        #40

        A = 0;

        #10

        clk = 1;

        #50

        clk = 0;

        #50

        clk = 1;

        #50

        clk = 0;

        #30

        A = 1;

        #20

        clk = 1;

        #50

        clk = 0;

        #30

        A = 1;

        #20

        clk = 1;

        #50

        clk = 0;

        #50

        clk = 1;

        #50

        clk = 0;

        #50

        clk = 1;

        #50

        clk = 0;

        #50

        clk = 1;

        #30

        A = 0;

        #20

        clk = 0;

        #50

        clk = 1;

        #10

        A = 1;

        #40

        clk = 0;

        #50

        clk = 1;

        #50

        clk = 0;
    end
always@(clk == 1)// Prinitng output only at positive clock edges
    if($time%100 != 0 && $time%50 == 0)
        $display("time=%d:A = %b,clk = %b,rst = %b,Y = %b\n",$time-100,A,clk,rst,Y);
endmodule

zero_one_detector/zero_one_detector.vcd
$date
	Wed May  9 15:36:31 2018
$end
$version
	Icarus Verilog
$end
$timescale
	1s
$end
$scope module seq_tb $end
$var wire 1 ! Y $end
$var reg 1 " A $end
$var reg 1 # clk $end
$var reg 1 $ rst $end
$scope module uut $end
$var wire 1 " A $end
$var wire 1 # clk $end
$var wire 1 $ rst $end
$var reg 1 ! Y $end
$var reg 2 % curr_state [1:0] $end
$var reg 2 & nxt_state [1:0] $end
$upscope $end
$upscope $end
$enddefinitions $end
#0
$dumpvars
bx &
bx %
1$
x#
x"
x!
$end
#50
0$
#100
b0 &
0"
0#
#150
b1 &
b0 %
0!
1#
#200
0#
#250
b1 %
1#
#270
b10 &
1"
#300
0#
#350
b0 &
b10 %
1!
1#
#360
b1 &
0"
#400
0#
#450
b1 %
0!
1#
#500
0#
#510
b10 &
1"
#550
b0 &
b10 %
1!
1#
#600
0#
#640
b1 &
0"
#650
b1 %
0!
1#
#700
0#
#750
1#
#800
0#
#830
b10 &
1"
#850
b0 &
b10 %
1!
1#
#900
0#
#950
b0 %
0!
1#
#1000
0#
#1050
1#
#1100
0#
#1150
1#
#1200
0#
#1250
1#
#1280
b1 &
0"
#1300
0#
#1350
b1 %
1#
#1360
b10 &
1"
#1400
0#
#1450
b0 &
b10 %
1!
1#
